
{"items":[{"name":"MASES.EntityFrameworkCore.KNet","href":"MASES.EntityFrameworkCore.KNet.html","topicHref":"MASES.EntityFrameworkCore.KNet.html","topicUid":"MASES.EntityFrameworkCore.KNet","items":[{"name":"KEFCore","href":"MASES.EntityFrameworkCore.KNet.KEFCore.html","topicHref":"MASES.EntityFrameworkCore.KNet.KEFCore.html","topicUid":"MASES.EntityFrameworkCore.KNet.KEFCore"},{"name":"KafkaDatabaseFacadeExtensions","href":"MASES.EntityFrameworkCore.KNet.KafkaDatabaseFacadeExtensions.html","topicHref":"MASES.EntityFrameworkCore.KNet.KafkaDatabaseFacadeExtensions.html","topicUid":"MASES.EntityFrameworkCore.KNet.KafkaDatabaseFacadeExtensions"},{"name":"KafkaDbContextOptionsExtensions","href":"MASES.EntityFrameworkCore.KNet.KafkaDbContextOptionsExtensions.html","topicHref":"MASES.EntityFrameworkCore.KNet.KafkaDbContextOptionsExtensions.html","topicUid":"MASES.EntityFrameworkCore.KNet.KafkaDbContextOptionsExtensions"},{"name":"KafkaEntityTypeBuilderExtensions","href":"MASES.EntityFrameworkCore.KNet.KafkaEntityTypeBuilderExtensions.html","topicHref":"MASES.EntityFrameworkCore.KNet.KafkaEntityTypeBuilderExtensions.html","topicUid":"MASES.EntityFrameworkCore.KNet.KafkaEntityTypeBuilderExtensions"},{"name":"KafkaEntityTypeExtensions","href":"MASES.EntityFrameworkCore.KNet.KafkaEntityTypeExtensions.html","topicHref":"MASES.EntityFrameworkCore.KNet.KafkaEntityTypeExtensions.html","topicUid":"MASES.EntityFrameworkCore.KNet.KafkaEntityTypeExtensions"}]},{"name":"MASES.EntityFrameworkCore.KNet.Design.Internal","href":"MASES.EntityFrameworkCore.KNet.Design.Internal.html","topicHref":"MASES.EntityFrameworkCore.KNet.Design.Internal.html","topicUid":"MASES.EntityFrameworkCore.KNet.Design.Internal","items":[{"name":"KafkaCSharpRuntimeAnnotationCodeGenerator","href":"MASES.EntityFrameworkCore.KNet.Design.Internal.KafkaCSharpRuntimeAnnotationCodeGenerator.html","topicHref":"MASES.EntityFrameworkCore.KNet.Design.Internal.KafkaCSharpRuntimeAnnotationCodeGenerator.html","topicUid":"MASES.EntityFrameworkCore.KNet.Design.Internal.KafkaCSharpRuntimeAnnotationCodeGenerator"},{"name":"KafkaDesignTimeServices","href":"MASES.EntityFrameworkCore.KNet.Design.Internal.KafkaDesignTimeServices.html","topicHref":"MASES.EntityFrameworkCore.KNet.Design.Internal.KafkaDesignTimeServices.html","topicUid":"MASES.EntityFrameworkCore.KNet.Design.Internal.KafkaDesignTimeServices"}]},{"name":"MASES.EntityFrameworkCore.KNet.Diagnostics","href":"MASES.EntityFrameworkCore.KNet.Diagnostics.html","topicHref":"MASES.EntityFrameworkCore.KNet.Diagnostics.html","topicUid":"MASES.EntityFrameworkCore.KNet.Diagnostics","items":[{"name":"KafkaEventId","href":"MASES.EntityFrameworkCore.KNet.Diagnostics.KafkaEventId.html","topicHref":"MASES.EntityFrameworkCore.KNet.Diagnostics.KafkaEventId.html","topicUid":"MASES.EntityFrameworkCore.KNet.Diagnostics.KafkaEventId"}]},{"name":"MASES.EntityFrameworkCore.KNet.Diagnostics.Internal","href":"MASES.EntityFrameworkCore.KNet.Diagnostics.Internal.html","topicHref":"MASES.EntityFrameworkCore.KNet.Diagnostics.Internal.html","topicUid":"MASES.EntityFrameworkCore.KNet.Diagnostics.Internal","items":[{"name":"KafkaLoggerExtensions","href":"MASES.EntityFrameworkCore.KNet.Diagnostics.Internal.KafkaLoggerExtensions.html","topicHref":"MASES.EntityFrameworkCore.KNet.Diagnostics.Internal.KafkaLoggerExtensions.html","topicUid":"MASES.EntityFrameworkCore.KNet.Diagnostics.Internal.KafkaLoggerExtensions"},{"name":"KafkaLoggingDefinitions","href":"MASES.EntityFrameworkCore.KNet.Diagnostics.Internal.KafkaLoggingDefinitions.html","topicHref":"MASES.EntityFrameworkCore.KNet.Diagnostics.Internal.KafkaLoggingDefinitions.html","topicUid":"MASES.EntityFrameworkCore.KNet.Diagnostics.Internal.KafkaLoggingDefinitions"}]},{"name":"MASES.EntityFrameworkCore.KNet.Infrastructure","href":"MASES.EntityFrameworkCore.KNet.Infrastructure.html","topicHref":"MASES.EntityFrameworkCore.KNet.Infrastructure.html","topicUid":"MASES.EntityFrameworkCore.KNet.Infrastructure","items":[{"name":"IKafkaDbContextOptionsBuilderInfrastructure","href":"MASES.EntityFrameworkCore.KNet.Infrastructure.IKafkaDbContextOptionsBuilderInfrastructure.html","topicHref":"MASES.EntityFrameworkCore.KNet.Infrastructure.IKafkaDbContextOptionsBuilderInfrastructure.html","topicUid":"MASES.EntityFrameworkCore.KNet.Infrastructure.IKafkaDbContextOptionsBuilderInfrastructure"},{"name":"KafkaDbContext","href":"MASES.EntityFrameworkCore.KNet.Infrastructure.KafkaDbContext.html","topicHref":"MASES.EntityFrameworkCore.KNet.Infrastructure.KafkaDbContext.html","topicUid":"MASES.EntityFrameworkCore.KNet.Infrastructure.KafkaDbContext"},{"name":"KafkaDbContextOptionsBuilder","href":"MASES.EntityFrameworkCore.KNet.Infrastructure.KafkaDbContextOptionsBuilder.html","topicHref":"MASES.EntityFrameworkCore.KNet.Infrastructure.KafkaDbContextOptionsBuilder.html","topicUid":"MASES.EntityFrameworkCore.KNet.Infrastructure.KafkaDbContextOptionsBuilder"}]},{"name":"MASES.EntityFrameworkCore.KNet.Infrastructure.Internal","href":"MASES.EntityFrameworkCore.KNet.Infrastructure.Internal.html","topicHref":"MASES.EntityFrameworkCore.KNet.Infrastructure.Internal.html","topicUid":"MASES.EntityFrameworkCore.KNet.Infrastructure.Internal","items":[{"name":"IKafkaSingletonOptions","href":"MASES.EntityFrameworkCore.KNet.Infrastructure.Internal.IKafkaSingletonOptions.html","topicHref":"MASES.EntityFrameworkCore.KNet.Infrastructure.Internal.IKafkaSingletonOptions.html","topicUid":"MASES.EntityFrameworkCore.KNet.Infrastructure.Internal.IKafkaSingletonOptions"},{"name":"KafkaModelValidator","href":"MASES.EntityFrameworkCore.KNet.Infrastructure.Internal.KafkaModelValidator.html","topicHref":"MASES.EntityFrameworkCore.KNet.Infrastructure.Internal.KafkaModelValidator.html","topicUid":"MASES.EntityFrameworkCore.KNet.Infrastructure.Internal.KafkaModelValidator"},{"name":"KafkaOptionsExtension","href":"MASES.EntityFrameworkCore.KNet.Infrastructure.Internal.KafkaOptionsExtension.html","topicHref":"MASES.EntityFrameworkCore.KNet.Infrastructure.Internal.KafkaOptionsExtension.html","topicUid":"MASES.EntityFrameworkCore.KNet.Infrastructure.Internal.KafkaOptionsExtension"},{"name":"KafkaSingletonOptions","href":"MASES.EntityFrameworkCore.KNet.Infrastructure.Internal.KafkaSingletonOptions.html","topicHref":"MASES.EntityFrameworkCore.KNet.Infrastructure.Internal.KafkaSingletonOptions.html","topicUid":"MASES.EntityFrameworkCore.KNet.Infrastructure.Internal.KafkaSingletonOptions"}]},{"name":"MASES.EntityFrameworkCore.KNet.Internal","href":"MASES.EntityFrameworkCore.KNet.Internal.html","topicHref":"MASES.EntityFrameworkCore.KNet.Internal.html","topicUid":"MASES.EntityFrameworkCore.KNet.Internal","items":[{"name":"KafkaResources","href":"MASES.EntityFrameworkCore.KNet.Internal.KafkaResources.html","topicHref":"MASES.EntityFrameworkCore.KNet.Internal.KafkaResources.html","topicUid":"MASES.EntityFrameworkCore.KNet.Internal.KafkaResources"},{"name":"KafkaStrings","href":"MASES.EntityFrameworkCore.KNet.Internal.KafkaStrings.html","topicHref":"MASES.EntityFrameworkCore.KNet.Internal.KafkaStrings.html","topicUid":"MASES.EntityFrameworkCore.KNet.Internal.KafkaStrings"}]},{"name":"MASES.EntityFrameworkCore.KNet.Metadata.Conventions","href":"MASES.EntityFrameworkCore.KNet.Metadata.Conventions.html","topicHref":"MASES.EntityFrameworkCore.KNet.Metadata.Conventions.html","topicUid":"MASES.EntityFrameworkCore.KNet.Metadata.Conventions","items":[{"name":"DefiningQueryRewritingConvention","href":"MASES.EntityFrameworkCore.KNet.Metadata.Conventions.DefiningQueryRewritingConvention.html","topicHref":"MASES.EntityFrameworkCore.KNet.Metadata.Conventions.DefiningQueryRewritingConvention.html","topicUid":"MASES.EntityFrameworkCore.KNet.Metadata.Conventions.DefiningQueryRewritingConvention"},{"name":"KafkaConventionSetBuilder","href":"MASES.EntityFrameworkCore.KNet.Metadata.Conventions.KafkaConventionSetBuilder.html","topicHref":"MASES.EntityFrameworkCore.KNet.Metadata.Conventions.KafkaConventionSetBuilder.html","topicUid":"MASES.EntityFrameworkCore.KNet.Metadata.Conventions.KafkaConventionSetBuilder"}]},{"name":"MASES.EntityFrameworkCore.KNet.Query.Internal","href":"MASES.EntityFrameworkCore.KNet.Query.Internal.html","topicHref":"MASES.EntityFrameworkCore.KNet.Query.Internal.html","topicUid":"MASES.EntityFrameworkCore.KNet.Query.Internal","items":[{"name":"AnonymousObject","href":"MASES.EntityFrameworkCore.KNet.Query.Internal.AnonymousObject.html","topicHref":"MASES.EntityFrameworkCore.KNet.Query.Internal.AnonymousObject.html","topicUid":"MASES.EntityFrameworkCore.KNet.Query.Internal.AnonymousObject"},{"name":"CollectionResultShaperExpression","href":"MASES.EntityFrameworkCore.KNet.Query.Internal.CollectionResultShaperExpression.html","topicHref":"MASES.EntityFrameworkCore.KNet.Query.Internal.CollectionResultShaperExpression.html","topicUid":"MASES.EntityFrameworkCore.KNet.Query.Internal.CollectionResultShaperExpression"},{"name":"EntityProjectionExpression","href":"MASES.EntityFrameworkCore.KNet.Query.Internal.EntityProjectionExpression.html","topicHref":"MASES.EntityFrameworkCore.KNet.Query.Internal.EntityProjectionExpression.html","topicUid":"MASES.EntityFrameworkCore.KNet.Query.Internal.EntityProjectionExpression"},{"name":"KafkaExpressionTranslatingExpressionVisitor","href":"MASES.EntityFrameworkCore.KNet.Query.Internal.KafkaExpressionTranslatingExpressionVisitor.html","topicHref":"MASES.EntityFrameworkCore.KNet.Query.Internal.KafkaExpressionTranslatingExpressionVisitor.html","topicUid":"MASES.EntityFrameworkCore.KNet.Query.Internal.KafkaExpressionTranslatingExpressionVisitor"},{"name":"KafkaProjectionBindingExpressionVisitor","href":"MASES.EntityFrameworkCore.KNet.Query.Internal.KafkaProjectionBindingExpressionVisitor.html","topicHref":"MASES.EntityFrameworkCore.KNet.Query.Internal.KafkaProjectionBindingExpressionVisitor.html","topicUid":"MASES.EntityFrameworkCore.KNet.Query.Internal.KafkaProjectionBindingExpressionVisitor"},{"name":"KafkaQueryContext","href":"MASES.EntityFrameworkCore.KNet.Query.Internal.KafkaQueryContext.html","topicHref":"MASES.EntityFrameworkCore.KNet.Query.Internal.KafkaQueryContext.html","topicUid":"MASES.EntityFrameworkCore.KNet.Query.Internal.KafkaQueryContext"},{"name":"KafkaQueryContextFactory","href":"MASES.EntityFrameworkCore.KNet.Query.Internal.KafkaQueryContextFactory.html","topicHref":"MASES.EntityFrameworkCore.KNet.Query.Internal.KafkaQueryContextFactory.html","topicUid":"MASES.EntityFrameworkCore.KNet.Query.Internal.KafkaQueryContextFactory"},{"name":"KafkaQueryExpression","href":"MASES.EntityFrameworkCore.KNet.Query.Internal.KafkaQueryExpression.html","topicHref":"MASES.EntityFrameworkCore.KNet.Query.Internal.KafkaQueryExpression.html","topicUid":"MASES.EntityFrameworkCore.KNet.Query.Internal.KafkaQueryExpression"},{"name":"KafkaQueryTranslationPreprocessor","href":"MASES.EntityFrameworkCore.KNet.Query.Internal.KafkaQueryTranslationPreprocessor.html","topicHref":"MASES.EntityFrameworkCore.KNet.Query.Internal.KafkaQueryTranslationPreprocessor.html","topicUid":"MASES.EntityFrameworkCore.KNet.Query.Internal.KafkaQueryTranslationPreprocessor"},{"name":"KafkaQueryTranslationPreprocessorFactory","href":"MASES.EntityFrameworkCore.KNet.Query.Internal.KafkaQueryTranslationPreprocessorFactory.html","topicHref":"MASES.EntityFrameworkCore.KNet.Query.Internal.KafkaQueryTranslationPreprocessorFactory.html","topicUid":"MASES.EntityFrameworkCore.KNet.Query.Internal.KafkaQueryTranslationPreprocessorFactory"},{"name":"KafkaQueryableMethodTranslatingExpressionVisitor","href":"MASES.EntityFrameworkCore.KNet.Query.Internal.KafkaQueryableMethodTranslatingExpressionVisitor.html","topicHref":"MASES.EntityFrameworkCore.KNet.Query.Internal.KafkaQueryableMethodTranslatingExpressionVisitor.html","topicUid":"MASES.EntityFrameworkCore.KNet.Query.Internal.KafkaQueryableMethodTranslatingExpressionVisitor"},{"name":"KafkaQueryableMethodTranslatingExpressionVisitorFactory","href":"MASES.EntityFrameworkCore.KNet.Query.Internal.KafkaQueryableMethodTranslatingExpressionVisitorFactory.html","topicHref":"MASES.EntityFrameworkCore.KNet.Query.Internal.KafkaQueryableMethodTranslatingExpressionVisitorFactory.html","topicUid":"MASES.EntityFrameworkCore.KNet.Query.Internal.KafkaQueryableMethodTranslatingExpressionVisitorFactory"},{"name":"KafkaShapedQueryCompilingExpressionVisitor","href":"MASES.EntityFrameworkCore.KNet.Query.Internal.KafkaShapedQueryCompilingExpressionVisitor.html","topicHref":"MASES.EntityFrameworkCore.KNet.Query.Internal.KafkaShapedQueryCompilingExpressionVisitor.html","topicUid":"MASES.EntityFrameworkCore.KNet.Query.Internal.KafkaShapedQueryCompilingExpressionVisitor"},{"name":"KafkaShapedQueryCompilingExpressionVisitorFactory","href":"MASES.EntityFrameworkCore.KNet.Query.Internal.KafkaShapedQueryCompilingExpressionVisitorFactory.html","topicHref":"MASES.EntityFrameworkCore.KNet.Query.Internal.KafkaShapedQueryCompilingExpressionVisitorFactory.html","topicUid":"MASES.EntityFrameworkCore.KNet.Query.Internal.KafkaShapedQueryCompilingExpressionVisitorFactory"},{"name":"KafkaTableExpression","href":"MASES.EntityFrameworkCore.KNet.Query.Internal.KafkaTableExpression.html","topicHref":"MASES.EntityFrameworkCore.KNet.Query.Internal.KafkaTableExpression.html","topicUid":"MASES.EntityFrameworkCore.KNet.Query.Internal.KafkaTableExpression"},{"name":"SingleResultShaperExpression","href":"MASES.EntityFrameworkCore.KNet.Query.Internal.SingleResultShaperExpression.html","topicHref":"MASES.EntityFrameworkCore.KNet.Query.Internal.SingleResultShaperExpression.html","topicUid":"MASES.EntityFrameworkCore.KNet.Query.Internal.SingleResultShaperExpression"}]},{"name":"MASES.EntityFrameworkCore.KNet.Serialization","href":"MASES.EntityFrameworkCore.KNet.Serialization.html","topicHref":"MASES.EntityFrameworkCore.KNet.Serialization.html","topicUid":"MASES.EntityFrameworkCore.KNet.Serialization","items":[{"name":"EntityExtractor","href":"MASES.EntityFrameworkCore.KNet.Serialization.EntityExtractor.html","topicHref":"MASES.EntityFrameworkCore.KNet.Serialization.EntityExtractor.html","topicUid":"MASES.EntityFrameworkCore.KNet.Serialization.EntityExtractor"},{"name":"IValueContainer<T>","href":"MASES.EntityFrameworkCore.KNet.Serialization.IValueContainer-1.html","topicHref":"MASES.EntityFrameworkCore.KNet.Serialization.IValueContainer-1.html","topicUid":"MASES.EntityFrameworkCore.KNet.Serialization.IValueContainer`1"}]},{"name":"MASES.EntityFrameworkCore.KNet.Serialization.Avro","href":"MASES.EntityFrameworkCore.KNet.Serialization.Avro.html","topicHref":"MASES.EntityFrameworkCore.KNet.Serialization.Avro.html","topicUid":"MASES.EntityFrameworkCore.KNet.Serialization.Avro","items":[{"name":"AvroKEFCoreSerDes","href":"MASES.EntityFrameworkCore.KNet.Serialization.Avro.AvroKEFCoreSerDes.html","topicHref":"MASES.EntityFrameworkCore.KNet.Serialization.Avro.AvroKEFCoreSerDes.html","topicUid":"MASES.EntityFrameworkCore.KNet.Serialization.Avro.AvroKEFCoreSerDes"},{"name":"AvroKEFCoreSerDes.Key","href":"MASES.EntityFrameworkCore.KNet.Serialization.Avro.AvroKEFCoreSerDes.Key.html","topicHref":"MASES.EntityFrameworkCore.KNet.Serialization.Avro.AvroKEFCoreSerDes.Key.html","topicUid":"MASES.EntityFrameworkCore.KNet.Serialization.Avro.AvroKEFCoreSerDes.Key"},{"name":"AvroKEFCoreSerDes.Key.Binary<T>","href":"MASES.EntityFrameworkCore.KNet.Serialization.Avro.AvroKEFCoreSerDes.Key.Binary-1.html","topicHref":"MASES.EntityFrameworkCore.KNet.Serialization.Avro.AvroKEFCoreSerDes.Key.Binary-1.html","topicUid":"MASES.EntityFrameworkCore.KNet.Serialization.Avro.AvroKEFCoreSerDes.Key.Binary`1"},{"name":"AvroKEFCoreSerDes.Key.Json<T>","href":"MASES.EntityFrameworkCore.KNet.Serialization.Avro.AvroKEFCoreSerDes.Key.Json-1.html","topicHref":"MASES.EntityFrameworkCore.KNet.Serialization.Avro.AvroKEFCoreSerDes.Key.Json-1.html","topicUid":"MASES.EntityFrameworkCore.KNet.Serialization.Avro.AvroKEFCoreSerDes.Key.Json`1"},{"name":"AvroKEFCoreSerDes.ValueContainer","href":"MASES.EntityFrameworkCore.KNet.Serialization.Avro.AvroKEFCoreSerDes.ValueContainer.html","topicHref":"MASES.EntityFrameworkCore.KNet.Serialization.Avro.AvroKEFCoreSerDes.ValueContainer.html","topicUid":"MASES.EntityFrameworkCore.KNet.Serialization.Avro.AvroKEFCoreSerDes.ValueContainer"},{"name":"AvroKEFCoreSerDes.ValueContainer.Binary<T>","href":"MASES.EntityFrameworkCore.KNet.Serialization.Avro.AvroKEFCoreSerDes.ValueContainer.Binary-1.html","topicHref":"MASES.EntityFrameworkCore.KNet.Serialization.Avro.AvroKEFCoreSerDes.ValueContainer.Binary-1.html","topicUid":"MASES.EntityFrameworkCore.KNet.Serialization.Avro.AvroKEFCoreSerDes.ValueContainer.Binary`1"},{"name":"AvroKEFCoreSerDes.ValueContainer.Json<T>","href":"MASES.EntityFrameworkCore.KNet.Serialization.Avro.AvroKEFCoreSerDes.ValueContainer.Json-1.html","topicHref":"MASES.EntityFrameworkCore.KNet.Serialization.Avro.AvroKEFCoreSerDes.ValueContainer.Json-1.html","topicUid":"MASES.EntityFrameworkCore.KNet.Serialization.Avro.AvroKEFCoreSerDes.ValueContainer.Json`1"}]},{"name":"MASES.EntityFrameworkCore.KNet.Serialization.Avro.Compiler","href":"MASES.EntityFrameworkCore.KNet.Serialization.Avro.Compiler.html","topicHref":"MASES.EntityFrameworkCore.KNet.Serialization.Avro.Compiler.html","topicUid":"MASES.EntityFrameworkCore.KNet.Serialization.Avro.Compiler","items":[{"name":"AvroSerializationHelper","href":"MASES.EntityFrameworkCore.KNet.Serialization.Avro.Compiler.AvroSerializationHelper.html","topicHref":"MASES.EntityFrameworkCore.KNet.Serialization.Avro.Compiler.AvroSerializationHelper.html","topicUid":"MASES.EntityFrameworkCore.KNet.Serialization.Avro.Compiler.AvroSerializationHelper"}]},{"name":"MASES.EntityFrameworkCore.KNet.Serialization.Avro.Storage","href":"MASES.EntityFrameworkCore.KNet.Serialization.Avro.Storage.html","topicHref":"MASES.EntityFrameworkCore.KNet.Serialization.Avro.Storage.html","topicUid":"MASES.EntityFrameworkCore.KNet.Serialization.Avro.Storage","items":[{"name":"AvroKeyContainer","href":"MASES.EntityFrameworkCore.KNet.Serialization.Avro.Storage.AvroKeyContainer.html","topicHref":"MASES.EntityFrameworkCore.KNet.Serialization.Avro.Storage.AvroKeyContainer.html","topicUid":"MASES.EntityFrameworkCore.KNet.Serialization.Avro.Storage.AvroKeyContainer"},{"name":"AvroValueContainer","href":"MASES.EntityFrameworkCore.KNet.Serialization.Avro.Storage.AvroValueContainer.html","topicHref":"MASES.EntityFrameworkCore.KNet.Serialization.Avro.Storage.AvroValueContainer.html","topicUid":"MASES.EntityFrameworkCore.KNet.Serialization.Avro.Storage.AvroValueContainer"},{"name":"AvroValueContainer<TKey>","href":"MASES.EntityFrameworkCore.KNet.Serialization.Avro.Storage.AvroValueContainer-1.html","topicHref":"MASES.EntityFrameworkCore.KNet.Serialization.Avro.Storage.AvroValueContainer-1.html","topicUid":"MASES.EntityFrameworkCore.KNet.Serialization.Avro.Storage.AvroValueContainer`1"},{"name":"PropertyDataRecord","href":"MASES.EntityFrameworkCore.KNet.Serialization.Avro.Storage.PropertyDataRecord.html","topicHref":"MASES.EntityFrameworkCore.KNet.Serialization.Avro.Storage.PropertyDataRecord.html","topicUid":"MASES.EntityFrameworkCore.KNet.Serialization.Avro.Storage.PropertyDataRecord"}]},{"name":"MASES.EntityFrameworkCore.KNet.Serialization.Json","href":"MASES.EntityFrameworkCore.KNet.Serialization.Json.html","topicHref":"MASES.EntityFrameworkCore.KNet.Serialization.Json.html","topicUid":"MASES.EntityFrameworkCore.KNet.Serialization.Json","items":[{"name":"DefaultKEFCoreSerDes","href":"MASES.EntityFrameworkCore.KNet.Serialization.Json.DefaultKEFCoreSerDes.html","topicHref":"MASES.EntityFrameworkCore.KNet.Serialization.Json.DefaultKEFCoreSerDes.html","topicUid":"MASES.EntityFrameworkCore.KNet.Serialization.Json.DefaultKEFCoreSerDes"},{"name":"DefaultKEFCoreSerDes.Key","href":"MASES.EntityFrameworkCore.KNet.Serialization.Json.DefaultKEFCoreSerDes.Key.html","topicHref":"MASES.EntityFrameworkCore.KNet.Serialization.Json.DefaultKEFCoreSerDes.Key.html","topicUid":"MASES.EntityFrameworkCore.KNet.Serialization.Json.DefaultKEFCoreSerDes.Key"},{"name":"DefaultKEFCoreSerDes.Key.Json<T>","href":"MASES.EntityFrameworkCore.KNet.Serialization.Json.DefaultKEFCoreSerDes.Key.Json-1.html","topicHref":"MASES.EntityFrameworkCore.KNet.Serialization.Json.DefaultKEFCoreSerDes.Key.Json-1.html","topicUid":"MASES.EntityFrameworkCore.KNet.Serialization.Json.DefaultKEFCoreSerDes.Key.Json`1"},{"name":"DefaultKEFCoreSerDes.ValueContainer","href":"MASES.EntityFrameworkCore.KNet.Serialization.Json.DefaultKEFCoreSerDes.ValueContainer.html","topicHref":"MASES.EntityFrameworkCore.KNet.Serialization.Json.DefaultKEFCoreSerDes.ValueContainer.html","topicUid":"MASES.EntityFrameworkCore.KNet.Serialization.Json.DefaultKEFCoreSerDes.ValueContainer"},{"name":"DefaultKEFCoreSerDes.ValueContainer.Json<T>","href":"MASES.EntityFrameworkCore.KNet.Serialization.Json.DefaultKEFCoreSerDes.ValueContainer.Json-1.html","topicHref":"MASES.EntityFrameworkCore.KNet.Serialization.Json.DefaultKEFCoreSerDes.ValueContainer.Json-1.html","topicUid":"MASES.EntityFrameworkCore.KNet.Serialization.Json.DefaultKEFCoreSerDes.ValueContainer.Json`1"}]},{"name":"MASES.EntityFrameworkCore.KNet.Serialization.Json.Storage","href":"MASES.EntityFrameworkCore.KNet.Serialization.Json.Storage.html","topicHref":"MASES.EntityFrameworkCore.KNet.Serialization.Json.Storage.html","topicUid":"MASES.EntityFrameworkCore.KNet.Serialization.Json.Storage","items":[{"name":"DefaultValueContainer<TKey>","href":"MASES.EntityFrameworkCore.KNet.Serialization.Json.Storage.DefaultValueContainer-1.html","topicHref":"MASES.EntityFrameworkCore.KNet.Serialization.Json.Storage.DefaultValueContainer-1.html","topicUid":"MASES.EntityFrameworkCore.KNet.Serialization.Json.Storage.DefaultValueContainer`1"},{"name":"PropertyData","href":"MASES.EntityFrameworkCore.KNet.Serialization.Json.Storage.PropertyData.html","topicHref":"MASES.EntityFrameworkCore.KNet.Serialization.Json.Storage.PropertyData.html","topicUid":"MASES.EntityFrameworkCore.KNet.Serialization.Json.Storage.PropertyData"}]},{"name":"MASES.EntityFrameworkCore.KNet.Serialization.Protobuf","href":"MASES.EntityFrameworkCore.KNet.Serialization.Protobuf.html","topicHref":"MASES.EntityFrameworkCore.KNet.Serialization.Protobuf.html","topicUid":"MASES.EntityFrameworkCore.KNet.Serialization.Protobuf","items":[{"name":"ProtobufKEFCoreSerDes","href":"MASES.EntityFrameworkCore.KNet.Serialization.Protobuf.ProtobufKEFCoreSerDes.html","topicHref":"MASES.EntityFrameworkCore.KNet.Serialization.Protobuf.ProtobufKEFCoreSerDes.html","topicUid":"MASES.EntityFrameworkCore.KNet.Serialization.Protobuf.ProtobufKEFCoreSerDes"},{"name":"ProtobufKEFCoreSerDes.Key","href":"MASES.EntityFrameworkCore.KNet.Serialization.Protobuf.ProtobufKEFCoreSerDes.Key.html","topicHref":"MASES.EntityFrameworkCore.KNet.Serialization.Protobuf.ProtobufKEFCoreSerDes.Key.html","topicUid":"MASES.EntityFrameworkCore.KNet.Serialization.Protobuf.ProtobufKEFCoreSerDes.Key"},{"name":"ProtobufKEFCoreSerDes.Key.Binary<T>","href":"MASES.EntityFrameworkCore.KNet.Serialization.Protobuf.ProtobufKEFCoreSerDes.Key.Binary-1.html","topicHref":"MASES.EntityFrameworkCore.KNet.Serialization.Protobuf.ProtobufKEFCoreSerDes.Key.Binary-1.html","topicUid":"MASES.EntityFrameworkCore.KNet.Serialization.Protobuf.ProtobufKEFCoreSerDes.Key.Binary`1"},{"name":"ProtobufKEFCoreSerDes.ValueContainer","href":"MASES.EntityFrameworkCore.KNet.Serialization.Protobuf.ProtobufKEFCoreSerDes.ValueContainer.html","topicHref":"MASES.EntityFrameworkCore.KNet.Serialization.Protobuf.ProtobufKEFCoreSerDes.ValueContainer.html","topicUid":"MASES.EntityFrameworkCore.KNet.Serialization.Protobuf.ProtobufKEFCoreSerDes.ValueContainer"},{"name":"ProtobufKEFCoreSerDes.ValueContainer.Binary<T>","href":"MASES.EntityFrameworkCore.KNet.Serialization.Protobuf.ProtobufKEFCoreSerDes.ValueContainer.Binary-1.html","topicHref":"MASES.EntityFrameworkCore.KNet.Serialization.Protobuf.ProtobufKEFCoreSerDes.ValueContainer.Binary-1.html","topicUid":"MASES.EntityFrameworkCore.KNet.Serialization.Protobuf.ProtobufKEFCoreSerDes.ValueContainer.Binary`1"}]},{"name":"MASES.EntityFrameworkCore.KNet.Serialization.Protobuf.Storage","href":"MASES.EntityFrameworkCore.KNet.Serialization.Protobuf.Storage.html","topicHref":"MASES.EntityFrameworkCore.KNet.Serialization.Protobuf.Storage.html","topicUid":"MASES.EntityFrameworkCore.KNet.Serialization.Protobuf.Storage","items":[{"name":"GenericValue","href":"MASES.EntityFrameworkCore.KNet.Serialization.Protobuf.Storage.GenericValue.html","topicHref":"MASES.EntityFrameworkCore.KNet.Serialization.Protobuf.Storage.GenericValue.html","topicUid":"MASES.EntityFrameworkCore.KNet.Serialization.Protobuf.Storage.GenericValue"},{"name":"GenericValue.KindOneofCase","href":"MASES.EntityFrameworkCore.KNet.Serialization.Protobuf.Storage.GenericValue.KindOneofCase.html","topicHref":"MASES.EntityFrameworkCore.KNet.Serialization.Protobuf.Storage.GenericValue.KindOneofCase.html","topicUid":"MASES.EntityFrameworkCore.KNet.Serialization.Protobuf.Storage.GenericValue.KindOneofCase"},{"name":"GenericValueReflection","href":"MASES.EntityFrameworkCore.KNet.Serialization.Protobuf.Storage.GenericValueReflection.html","topicHref":"MASES.EntityFrameworkCore.KNet.Serialization.Protobuf.Storage.GenericValueReflection.html","topicUid":"MASES.EntityFrameworkCore.KNet.Serialization.Protobuf.Storage.GenericValueReflection"},{"name":"KeyContainer","href":"MASES.EntityFrameworkCore.KNet.Serialization.Protobuf.Storage.KeyContainer.html","topicHref":"MASES.EntityFrameworkCore.KNet.Serialization.Protobuf.Storage.KeyContainer.html","topicUid":"MASES.EntityFrameworkCore.KNet.Serialization.Protobuf.Storage.KeyContainer"},{"name":"KeyContainerReflection","href":"MASES.EntityFrameworkCore.KNet.Serialization.Protobuf.Storage.KeyContainerReflection.html","topicHref":"MASES.EntityFrameworkCore.KNet.Serialization.Protobuf.Storage.KeyContainerReflection.html","topicUid":"MASES.EntityFrameworkCore.KNet.Serialization.Protobuf.Storage.KeyContainerReflection"},{"name":"PrimaryKeyType","href":"MASES.EntityFrameworkCore.KNet.Serialization.Protobuf.Storage.PrimaryKeyType.html","topicHref":"MASES.EntityFrameworkCore.KNet.Serialization.Protobuf.Storage.PrimaryKeyType.html","topicUid":"MASES.EntityFrameworkCore.KNet.Serialization.Protobuf.Storage.PrimaryKeyType"},{"name":"PropertyDataRecord","href":"MASES.EntityFrameworkCore.KNet.Serialization.Protobuf.Storage.PropertyDataRecord.html","topicHref":"MASES.EntityFrameworkCore.KNet.Serialization.Protobuf.Storage.PropertyDataRecord.html","topicUid":"MASES.EntityFrameworkCore.KNet.Serialization.Protobuf.Storage.PropertyDataRecord"},{"name":"ProtobufValueContainer<TKey>","href":"MASES.EntityFrameworkCore.KNet.Serialization.Protobuf.Storage.ProtobufValueContainer-1.html","topicHref":"MASES.EntityFrameworkCore.KNet.Serialization.Protobuf.Storage.ProtobufValueContainer-1.html","topicUid":"MASES.EntityFrameworkCore.KNet.Serialization.Protobuf.Storage.ProtobufValueContainer`1"},{"name":"ValueContainer","href":"MASES.EntityFrameworkCore.KNet.Serialization.Protobuf.Storage.ValueContainer.html","topicHref":"MASES.EntityFrameworkCore.KNet.Serialization.Protobuf.Storage.ValueContainer.html","topicUid":"MASES.EntityFrameworkCore.KNet.Serialization.Protobuf.Storage.ValueContainer"},{"name":"ValueContainerReflection","href":"MASES.EntityFrameworkCore.KNet.Serialization.Protobuf.Storage.ValueContainerReflection.html","topicHref":"MASES.EntityFrameworkCore.KNet.Serialization.Protobuf.Storage.ValueContainerReflection.html","topicUid":"MASES.EntityFrameworkCore.KNet.Serialization.Protobuf.Storage.ValueContainerReflection"}]},{"name":"MASES.EntityFrameworkCore.KNet.Storage","href":"MASES.EntityFrameworkCore.KNet.Storage.html","topicHref":"MASES.EntityFrameworkCore.KNet.Storage.html","topicUid":"MASES.EntityFrameworkCore.KNet.Storage","items":[{"name":"EntityTypeChanged","href":"MASES.EntityFrameworkCore.KNet.Storage.EntityTypeChanged.html","topicHref":"MASES.EntityFrameworkCore.KNet.Storage.EntityTypeChanged.html","topicUid":"MASES.EntityFrameworkCore.KNet.Storage.EntityTypeChanged"},{"name":"EntityTypeChanged.ChangeKindType","href":"MASES.EntityFrameworkCore.KNet.Storage.EntityTypeChanged.ChangeKindType.html","topicHref":"MASES.EntityFrameworkCore.KNet.Storage.EntityTypeChanged.ChangeKindType.html","topicUid":"MASES.EntityFrameworkCore.KNet.Storage.EntityTypeChanged.ChangeKindType"}]},{"name":"MASES.EntityFrameworkCore.KNet.Storage.Internal","href":"MASES.EntityFrameworkCore.KNet.Storage.Internal.html","topicHref":"MASES.EntityFrameworkCore.KNet.Storage.Internal.html","topicUid":"MASES.EntityFrameworkCore.KNet.Storage.Internal","items":[{"name":"EntityTypeProducer<TKey, TValueContainer, TKeySerializer, TValueSerializer>","href":"MASES.EntityFrameworkCore.KNet.Storage.Internal.EntityTypeProducer-4.html","topicHref":"MASES.EntityFrameworkCore.KNet.Storage.Internal.EntityTypeProducer-4.html","topicUid":"MASES.EntityFrameworkCore.KNet.Storage.Internal.EntityTypeProducer`4"},{"name":"EntityTypeProducers","href":"MASES.EntityFrameworkCore.KNet.Storage.Internal.EntityTypeProducers.html","topicHref":"MASES.EntityFrameworkCore.KNet.Storage.Internal.EntityTypeProducers.html","topicUid":"MASES.EntityFrameworkCore.KNet.Storage.Internal.EntityTypeProducers"},{"name":"IEntityTypeProducer","href":"MASES.EntityFrameworkCore.KNet.Storage.Internal.IEntityTypeProducer.html","topicHref":"MASES.EntityFrameworkCore.KNet.Storage.Internal.IEntityTypeProducer.html","topicUid":"MASES.EntityFrameworkCore.KNet.Storage.Internal.IEntityTypeProducer"},{"name":"IKafkaCluster","href":"MASES.EntityFrameworkCore.KNet.Storage.Internal.IKafkaCluster.html","topicHref":"MASES.EntityFrameworkCore.KNet.Storage.Internal.IKafkaCluster.html","topicUid":"MASES.EntityFrameworkCore.KNet.Storage.Internal.IKafkaCluster"},{"name":"IKafkaClusterCache","href":"MASES.EntityFrameworkCore.KNet.Storage.Internal.IKafkaClusterCache.html","topicHref":"MASES.EntityFrameworkCore.KNet.Storage.Internal.IKafkaClusterCache.html","topicUid":"MASES.EntityFrameworkCore.KNet.Storage.Internal.IKafkaClusterCache"},{"name":"IKafkaDatabase","href":"MASES.EntityFrameworkCore.KNet.Storage.Internal.IKafkaDatabase.html","topicHref":"MASES.EntityFrameworkCore.KNet.Storage.Internal.IKafkaDatabase.html","topicUid":"MASES.EntityFrameworkCore.KNet.Storage.Internal.IKafkaDatabase"},{"name":"IKafkaRowBag","href":"MASES.EntityFrameworkCore.KNet.Storage.Internal.IKafkaRowBag.html","topicHref":"MASES.EntityFrameworkCore.KNet.Storage.Internal.IKafkaRowBag.html","topicUid":"MASES.EntityFrameworkCore.KNet.Storage.Internal.IKafkaRowBag"},{"name":"IKafkaStreamsBaseRetriever","href":"MASES.EntityFrameworkCore.KNet.Storage.Internal.IKafkaStreamsBaseRetriever.html","topicHref":"MASES.EntityFrameworkCore.KNet.Storage.Internal.IKafkaStreamsBaseRetriever.html","topicUid":"MASES.EntityFrameworkCore.KNet.Storage.Internal.IKafkaStreamsBaseRetriever"},{"name":"IKafkaTable","href":"MASES.EntityFrameworkCore.KNet.Storage.Internal.IKafkaTable.html","topicHref":"MASES.EntityFrameworkCore.KNet.Storage.Internal.IKafkaTable.html","topicUid":"MASES.EntityFrameworkCore.KNet.Storage.Internal.IKafkaTable"},{"name":"IKafkaTableFactory","href":"MASES.EntityFrameworkCore.KNet.Storage.Internal.IKafkaTableFactory.html","topicHref":"MASES.EntityFrameworkCore.KNet.Storage.Internal.IKafkaTableFactory.html","topicUid":"MASES.EntityFrameworkCore.KNet.Storage.Internal.IKafkaTableFactory"},{"name":"KafkaCluster","href":"MASES.EntityFrameworkCore.KNet.Storage.Internal.KafkaCluster.html","topicHref":"MASES.EntityFrameworkCore.KNet.Storage.Internal.KafkaCluster.html","topicUid":"MASES.EntityFrameworkCore.KNet.Storage.Internal.KafkaCluster"},{"name":"KafkaClusterCache","href":"MASES.EntityFrameworkCore.KNet.Storage.Internal.KafkaClusterCache.html","topicHref":"MASES.EntityFrameworkCore.KNet.Storage.Internal.KafkaClusterCache.html","topicUid":"MASES.EntityFrameworkCore.KNet.Storage.Internal.KafkaClusterCache"},{"name":"KafkaClusterCacheExtensions","href":"MASES.EntityFrameworkCore.KNet.Storage.Internal.KafkaClusterCacheExtensions.html","topicHref":"MASES.EntityFrameworkCore.KNet.Storage.Internal.KafkaClusterCacheExtensions.html","topicUid":"MASES.EntityFrameworkCore.KNet.Storage.Internal.KafkaClusterCacheExtensions"},{"name":"KafkaDatabase","href":"MASES.EntityFrameworkCore.KNet.Storage.Internal.KafkaDatabase.html","topicHref":"MASES.EntityFrameworkCore.KNet.Storage.Internal.KafkaDatabase.html","topicUid":"MASES.EntityFrameworkCore.KNet.Storage.Internal.KafkaDatabase"},{"name":"KafkaDatabaseCreator","href":"MASES.EntityFrameworkCore.KNet.Storage.Internal.KafkaDatabaseCreator.html","topicHref":"MASES.EntityFrameworkCore.KNet.Storage.Internal.KafkaDatabaseCreator.html","topicUid":"MASES.EntityFrameworkCore.KNet.Storage.Internal.KafkaDatabaseCreator"},{"name":"KafkaRowBag<TKey, TValueContainer>","href":"MASES.EntityFrameworkCore.KNet.Storage.Internal.KafkaRowBag-2.html","topicHref":"MASES.EntityFrameworkCore.KNet.Storage.Internal.KafkaRowBag-2.html","topicUid":"MASES.EntityFrameworkCore.KNet.Storage.Internal.KafkaRowBag`2"},{"name":"KafkaStreamsBaseRetriever<TKey, TValue, K, V>","href":"MASES.EntityFrameworkCore.KNet.Storage.Internal.KafkaStreamsBaseRetriever-4.html","topicHref":"MASES.EntityFrameworkCore.KNet.Storage.Internal.KafkaStreamsBaseRetriever-4.html","topicUid":"MASES.EntityFrameworkCore.KNet.Storage.Internal.KafkaStreamsBaseRetriever`4"},{"name":"KafkaStreamsTableRetriever<TKey, TValueContainer>","href":"MASES.EntityFrameworkCore.KNet.Storage.Internal.KafkaStreamsTableRetriever-2.html","topicHref":"MASES.EntityFrameworkCore.KNet.Storage.Internal.KafkaStreamsTableRetriever-2.html","topicUid":"MASES.EntityFrameworkCore.KNet.Storage.Internal.KafkaStreamsTableRetriever`2"},{"name":"KafkaTableFactory","href":"MASES.EntityFrameworkCore.KNet.Storage.Internal.KafkaTableFactory.html","topicHref":"MASES.EntityFrameworkCore.KNet.Storage.Internal.KafkaTableFactory.html","topicUid":"MASES.EntityFrameworkCore.KNet.Storage.Internal.KafkaTableFactory"},{"name":"KafkaTable<TKey, TValueContainer, TKeySerializer, TValueSerializer>","href":"MASES.EntityFrameworkCore.KNet.Storage.Internal.KafkaTable-4.html","topicHref":"MASES.EntityFrameworkCore.KNet.Storage.Internal.KafkaTable-4.html","topicUid":"MASES.EntityFrameworkCore.KNet.Storage.Internal.KafkaTable`4"},{"name":"KafkaTransaction","href":"MASES.EntityFrameworkCore.KNet.Storage.Internal.KafkaTransaction.html","topicHref":"MASES.EntityFrameworkCore.KNet.Storage.Internal.KafkaTransaction.html","topicUid":"MASES.EntityFrameworkCore.KNet.Storage.Internal.KafkaTransaction"},{"name":"KafkaTransactionManager","href":"MASES.EntityFrameworkCore.KNet.Storage.Internal.KafkaTransactionManager.html","topicHref":"MASES.EntityFrameworkCore.KNet.Storage.Internal.KafkaTransactionManager.html","topicUid":"MASES.EntityFrameworkCore.KNet.Storage.Internal.KafkaTransactionManager"},{"name":"KafkaTypeMapping","href":"MASES.EntityFrameworkCore.KNet.Storage.Internal.KafkaTypeMapping.html","topicHref":"MASES.EntityFrameworkCore.KNet.Storage.Internal.KafkaTypeMapping.html","topicUid":"MASES.EntityFrameworkCore.KNet.Storage.Internal.KafkaTypeMapping"},{"name":"KafkaTypeMappingSource","href":"MASES.EntityFrameworkCore.KNet.Storage.Internal.KafkaTypeMappingSource.html","topicHref":"MASES.EntityFrameworkCore.KNet.Storage.Internal.KafkaTypeMappingSource.html","topicUid":"MASES.EntityFrameworkCore.KNet.Storage.Internal.KafkaTypeMappingSource"}]},{"name":"MASES.EntityFrameworkCore.KNet.Templates","href":"MASES.EntityFrameworkCore.KNet.Templates.html","topicHref":"MASES.EntityFrameworkCore.KNet.Templates.html","topicUid":"MASES.EntityFrameworkCore.KNet.Templates","items":[{"name":"Blog","href":"MASES.EntityFrameworkCore.KNet.Templates.Blog.html","topicHref":"MASES.EntityFrameworkCore.KNet.Templates.Blog.html","topicUid":"MASES.EntityFrameworkCore.KNet.Templates.Blog"},{"name":"BloggingContext","href":"MASES.EntityFrameworkCore.KNet.Templates.BloggingContext.html","topicHref":"MASES.EntityFrameworkCore.KNet.Templates.BloggingContext.html","topicUid":"MASES.EntityFrameworkCore.KNet.Templates.BloggingContext"},{"name":"Post","href":"MASES.EntityFrameworkCore.KNet.Templates.Post.html","topicHref":"MASES.EntityFrameworkCore.KNet.Templates.Post.html","topicUid":"MASES.EntityFrameworkCore.KNet.Templates.Post"}]},{"name":"MASES.EntityFrameworkCore.KNet.ValueGeneration.Internal","href":"MASES.EntityFrameworkCore.KNet.ValueGeneration.Internal.html","topicHref":"MASES.EntityFrameworkCore.KNet.ValueGeneration.Internal.html","topicUid":"MASES.EntityFrameworkCore.KNet.ValueGeneration.Internal","items":[{"name":"IKafkaIntegerValueGenerator","href":"MASES.EntityFrameworkCore.KNet.ValueGeneration.Internal.IKafkaIntegerValueGenerator.html","topicHref":"MASES.EntityFrameworkCore.KNet.ValueGeneration.Internal.IKafkaIntegerValueGenerator.html","topicUid":"MASES.EntityFrameworkCore.KNet.ValueGeneration.Internal.IKafkaIntegerValueGenerator"},{"name":"KafkaIntegerValueGenerator<TValue>","href":"MASES.EntityFrameworkCore.KNet.ValueGeneration.Internal.KafkaIntegerValueGenerator-1.html","topicHref":"MASES.EntityFrameworkCore.KNet.ValueGeneration.Internal.KafkaIntegerValueGenerator-1.html","topicUid":"MASES.EntityFrameworkCore.KNet.ValueGeneration.Internal.KafkaIntegerValueGenerator`1"},{"name":"KafkaValueGeneratorSelector","href":"MASES.EntityFrameworkCore.KNet.ValueGeneration.Internal.KafkaValueGeneratorSelector.html","topicHref":"MASES.EntityFrameworkCore.KNet.ValueGeneration.Internal.KafkaValueGeneratorSelector.html","topicUid":"MASES.EntityFrameworkCore.KNet.ValueGeneration.Internal.KafkaValueGeneratorSelector"}]},{"name":"Microsoft.Extensions.DependencyInjection","href":"Microsoft.Extensions.DependencyInjection.html","topicHref":"Microsoft.Extensions.DependencyInjection.html","topicUid":"Microsoft.Extensions.DependencyInjection","items":[{"name":"KafkaServiceCollectionExtensions","href":"Microsoft.Extensions.DependencyInjection.KafkaServiceCollectionExtensions.html","topicHref":"Microsoft.Extensions.DependencyInjection.KafkaServiceCollectionExtensions.html","topicUid":"Microsoft.Extensions.DependencyInjection.KafkaServiceCollectionExtensions"}]}],"memberLayout":"SamePage"}
